<annotation><filename>011.png</filename><folder>texts</folder><size><height>614</height><width>410</width></size><object><name>Diagram</name><object><name>Drawing</name><bndbox><xmin>6</xmin><xmax>165</xmax><ymin>45</ymin><ymax>305</ymax></bndbox></object><object><name>TextLine</name><object><name>Word</name><bndbox><xmin>24</xmin><xmax>42</xmax><ymin>0</ymin><ymax>49</ymax></bndbox><text>Source</text></object><bndbox><xmin>24</xmin><xmax>42</xmax><ymin>0</ymin><ymax>49</ymax></bndbox><text>Source</text></object><object><name>TextLine</name><object><name>Word</name><bndbox><xmin>-1</xmin><xmax>18</xmax><ymin>182</ymin><ymax>225</ymax></bndbox><text>Gate</text></object><bndbox><xmin>-1</xmin><xmax>18</xmax><ymin>182</ymin><ymax>225</ymax></bndbox><text>Gate</text></object><object><name>TextLine</name><object><name>Word</name><bndbox><xmin>14</xmin><xmax>41</xmax><ymin>302</ymin><ymax>356</ymax></bndbox><text>Drain</text></object><bndbox><xmin>14</xmin><xmax>41</xmax><ymin>302</ymin><ymax>356</ymax></bndbox><text>Drain</text></object><object><name>TextLine</name><object><name>Word</name><bndbox><xmin>85</xmin><xmax>105</xmax><ymin>69</ymin><ymax>90</ymax></bndbox><text>N+</text></object><bndbox><xmin>85</xmin><xmax>105</xmax><ymin>69</ymin><ymax>90</ymax></bndbox><text>N+</text></object><object><name>TextLine</name><object><name>Word</name><bndbox><xmin>92</xmin><xmax>108</xmax><ymin>261</ymin><ymax>282</ymax></bndbox><text>N+</text></object><bndbox><xmin>92</xmin><xmax>108</xmax><ymin>261</ymin><ymax>282</ymax></bndbox><text>N+</text></object><object><name>TextLine</name><object><name>Word</name><bndbox><xmin>111</xmin><xmax>128</xmax><ymin>254</ymin><ymax>262</ymax></bndbox><text>P</text></object><bndbox><xmin>111</xmin><xmax>128</xmax><ymin>254</ymin><ymax>262</ymax></bndbox><text>P</text></object><object><name>TextLine</name><object><name>Word</name><bndbox><xmin>125</xmin><xmax>149</xmax><ymin>157</ymin><ymax>181</ymax></bndbox><text>VDS</text></object><bndbox><xmin>125</xmin><xmax>149</xmax><ymin>157</ymin><ymax>181</ymax></bndbox><text>VDS</text></object><bndbox><xmin>-1</xmin><xmax>165</xmax><ymin>0</ymin><ymax>356</ymax></bndbox></object><object><name>TextBlock</name><object><name>TextLine</name><object><name>Word</name><bndbox><xmin>60</xmin><xmax>77</xmax><ymin>380</ymin><ymax>403</ymax></bndbox><text>Or</text></object><object><name>Word</name><bndbox><xmin>66</xmin><xmax>81</xmax><ymin>420</ymin><ymax>449</ymax></bndbox><text>you</text></object><object><name>Word</name><bndbox><xmin>53</xmin><xmax>75</xmax><ymin>471</ymin><ymax>511</ymax></bndbox><text>could</text></object><object><name>Word</name><bndbox><xmin>51</xmin><xmax>75</xmax><ymin>522</ymin><ymax>561</ymax></bndbox><text>wish</text></object><bndbox><xmin>51</xmin><xmax>81</xmax><ymin>380</ymin><ymax>561</ymax></bndbox><text>Or you could wish</text></object><object><name>TextLine</name><object><name>Word</name><bndbox><xmin>94</xmin><xmax>105</xmax><ymin>321</ymin><ymax>361</ymax></bndbox><text>your</text></object><object><name>Word</name><bndbox><xmin>82</xmin><xmax>103</xmax><ymin>379</ymin><ymax>430</ymax></bndbox><text>daddy</text></object><object><name>Word</name><bndbox><xmin>83</xmin><xmax>103</xmax><ymin>445</ymin><ymax>490</ymax></bndbox><text>would</text></object><object><name>Word</name><bndbox><xmin>82</xmin><xmax>105</xmax><ymin>502</ymin><ymax>543</ymax></bndbox><text>really</text></object><object><name>Word</name><bndbox><xmin>85</xmin><xmax>100</xmax><ymin>550</ymin><ymax>566</ymax></bndbox><text>do</text></object><object><name>Word</name><bndbox><xmin>80</xmin><xmax>98</xmax><ymin>571</ymin><ymax>576</ymax></bndbox><text>it</text></object><bndbox><xmin>80</xmin><xmax>105</xmax><ymin>321</ymin><ymax>576</ymax></bndbox><text>your daddy would really do it</text></object><object><name>TextLine</name><object><name>Word</name><bndbox><xmin>123</xmin><xmax>123</xmax><ymin>314</ymin><ymax>315</ymax></bndbox><text>-</text></object><object><name>Word</name><bndbox><xmin>121</xmin><xmax>122</xmax><ymin>327</ymin><ymax>330</ymax></bndbox><text>-</text></object><object><name>Word</name><bndbox><xmin>111</xmin><xmax>129</xmax><ymin>344</ymin><ymax>368</ymax></bndbox><text>kill</text></object><object><name>Word</name><bndbox><xmin>110</xmin><xmax>132</xmax><ymin>380</ymin><ymax>435</ymax></bndbox><text>Gratt</text></object><object><name>Word</name><bndbox><xmin>110</xmin><xmax>133</xmax><ymin>445</ymin><ymax>499</ymax></bndbox><text>Shafer</text></object><object><name>Word</name><bndbox><xmin>112</xmin><xmax>131</xmax><ymin>517</ymin><ymax>542</ymax></bndbox><text>like</text></object><object><name>Word</name><bndbox><xmin>114</xmin><xmax>130</xmax><ymin>549</ymin><ymax>567</ymax></bndbox><text>he</text></object><bndbox><xmin>110</xmin><xmax>133</xmax><ymin>314</ymin><ymax>567</ymax></bndbox><text>- - kill Gratt Shafer like he</text></object><object><name>TextLine</name><object><name>Word</name><bndbox><xmin>136</xmin><xmax>155</xmax><ymin>256</ymin><ymax>293</ymax></bndbox><text>said</text></object><object><name>Word</name><bndbox><xmin>130</xmin><xmax>155</xmax><ymin>311</ymin><ymax>354</ymax></bndbox><text>when</text></object><object><name>Word</name><bndbox><xmin>147</xmin><xmax>161</xmax><ymin>368</ymin><ymax>401</ymax></bndbox><text>you</text></object><object><name>Word</name><bndbox><xmin>137</xmin><xmax>156</xmax><ymin>419</ymin><ymax>436</ymax></bndbox><text>all</text></object><object><name>Word</name><bndbox><xmin>137</xmin><xmax>155</xmax><ymin>450</ymin><ymax>476</ymax></bndbox><text>the</text></object><object><name>Word</name><bndbox><xmin>137</xmin><xmax>156</xmax><ymin>492</ymin><ymax>538</ymax></bndbox><text>time</text></object><object><name>Word</name><bndbox><xmin>157</xmin><xmax>164</xmax><ymin>548</ymin><ymax>550</ymax></bndbox><text>,</text></object><object><name>Word</name><bndbox><xmin>138</xmin><xmax>157</xmax><ymin>560</ymin><ymax>578</ymax></bndbox><text>all</text></object><bndbox><xmin>130</xmin><xmax>164</xmax><ymin>256</ymin><ymax>578</ymax></bndbox><text>said when you all the time , all</text></object><object><name>TextLine</name><object><name>Word</name><bndbox><xmin>157</xmin><xmax>191</xmax><ymin>186</ymin><ymax>244</ymax></bndbox><text>along</text></object><object><name>Word</name><bndbox><xmin>175</xmin><xmax>176</xmax><ymin>256</ymin><ymax>257</ymax></bndbox><text>,</text></object><object><name>Word</name><bndbox><xmin>159</xmin><xmax>180</xmax><ymin>276</ymin><ymax>324</ymax></bndbox><text>could</text></object><object><name>Word</name><bndbox><xmin>161</xmin><xmax>181</xmax><ymin>335</ymin><ymax>371</ymax></bndbox><text>feel</text></object><object><name>Word</name><bndbox><xmin>164</xmin><xmax>179</xmax><ymin>387</ymin><ymax>417</ymax></bndbox><text>the</text></object><object><name>Word</name><bndbox><xmin>170</xmin><xmax>181</xmax><ymin>432</ymin><ymax>482</ymax></bndbox><text>nerve</text></object><object><name>Word</name><bndbox><xmin>164</xmin><xmax>196</xmax><ymin>504</ymin><ymax>586</ymax></bndbox><text>draining</text></object><bndbox><xmin>157</xmin><xmax>196</xmax><ymin>186</ymin><ymax>586</ymax></bndbox><text>along , could feel the nerve draining</text></object><object><name>TextLine</name><object><name>Word</name><bndbox><xmin>188</xmin><xmax>208</xmax><ymin>177</ymin><ymax>209</ymax></bndbox><text>out</text></object><object><name>Word</name><bndbox><xmin>183</xmin><xmax>207</xmax><ymin>227</ymin><ymax>243</ymax></bndbox><text>of</text></object><object><name>Word</name><bndbox><xmin>186</xmin><xmax>208</xmax><ymin>265</ymin><ymax>306</ymax></bndbox><text>him</text></object><object><name>Word</name><bndbox><xmin>189</xmin><xmax>207</xmax><ymin>322</ymin><ymax>350</ymax></bndbox><text>like</text></object><object><name>Word</name><bndbox><xmin>185</xmin><xmax>205</xmax><ymin>371</ymin><ymax>396</ymax></bndbox><text>air</text></object><object><name>Word</name><bndbox><xmin>189</xmin><xmax>205</xmax><ymin>417</ymin><ymax>445</ymax></bndbox><text>out</text></object><object><name>Word</name><bndbox><xmin>187</xmin><xmax>207</xmax><ymin>466</ymin><ymax>484</ymax></bndbox><text>of</text></object><object><name>Word</name><bndbox><xmin>197</xmin><xmax>207</xmax><ymin>501</ymin><ymax>507</ymax></bndbox><text>a</text></object><object><name>Word</name><bndbox><xmin>185</xmin><xmax>222</xmax><ymin>524</ymin><ymax>612</ymax></bndbox><text>punctured</text></object><bndbox><xmin>183</xmin><xmax>222</xmax><ymin>177</ymin><ymax>612</ymax></bndbox><text>out of him like air out of a punctured</text></object><object><name>TextLine</name><object><name>Word</name><bndbox><xmin>212</xmin><xmax>231</xmax><ymin>28</ymin><ymax>64</ymax></bndbox><text>tire</text></object><object><name>Word</name><bndbox><xmin>208</xmin><xmax>230</xmax><ymin>84</ymin><ymax>141</ymax></bndbox><text>when</text></object><object><name>Word</name><bndbox><xmin>220</xmin><xmax>230</xmax><ymin>160</ymin><ymax>193</ymax></bndbox><text>you</text></object><object><name>Word</name><bndbox><xmin>220</xmin><xmax>232</xmax><ymin>208</ymin><ymax>233</ymax></bndbox><text>are</text></object><object><name>Word</name><bndbox><xmin>222</xmin><xmax>232</xmax><ymin>257</ymin><ymax>285</ymax></bndbox><text>on</text></object><object><name>Word</name><bndbox><xmin>224</xmin><xmax>232</xmax><ymin>304</ymin><ymax>312</ymax></bndbox><text>a</text></object><object><name>Word</name><bndbox><xmin>211</xmin><xmax>233</xmax><ymin>329</ymin><ymax>407</ymax></bndbox><text>muddy</text></object><object><name>Word</name><bndbox><xmin>214</xmin><xmax>235</xmax><ymin>430</ymin><ymax>474</ymax></bndbox><text>road</text></object><object><name>Word</name><bndbox><xmin>213</xmin><xmax>235</xmax><ymin>490</ymin><ymax>556</ymax></bndbox><text>alone</text></object><object><name>Word</name><bndbox><xmin>216</xmin><xmax>235</xmax><ymin>572</ymin><ymax>608</ymax></bndbox><text>and</text></object><bndbox><xmin>208</xmin><xmax>235</xmax><ymin>28</ymin><ymax>608</ymax></bndbox><text>tire when you are on a muddy road alone and</text></object><object><name>TextLine</name><object><name>Word</name><bndbox><xmin>238</xmin><xmax>260</xmax><ymin>29</ymin><ymax>40</ymax></bndbox><text>it</text></object><object><name>Word</name><bndbox><xmin>235</xmin><xmax>255</xmax><ymin>60</ymin><ymax>69</ymax></bndbox><text>is</text></object><object><name>Word</name><bndbox><xmin>236</xmin><xmax>272</xmax><ymin>87</ymin><ymax>172</ymax></bndbox><text>raining</text></object><object><name>Word</name><bndbox><xmin>239</xmin><xmax>256</xmax><ymin>195</ymin><ymax>229</ymax></bndbox><text>and</text></object><object><name>Word</name><bndbox><xmin>238</xmin><xmax>257</xmax><ymin>251</ymin><ymax>266</ymax></bndbox><text>at</text></object><object><name>Word</name><bndbox><xmin>240</xmin><xmax>273</xmax><ymin>286</ymin><ymax>343</ymax></bndbox><text>night</text></object><object><name>Word</name><bndbox><xmin>257</xmin><xmax>257</xmax><ymin>350</ymin><ymax>350</ymax></bndbox><text>.</text></object><bndbox><xmin>235</xmin><xmax>273</xmax><ymin>29</ymin><ymax>350</ymax></bndbox><text>it is raining and at night .</text></object><bndbox><xmin>51</xmin><xmax>273</xmax><ymin>28</ymin><ymax>612</ymax></bndbox></object><object><name>List</name><object><name>TextLine</name><object><name>Symbol</name><bndbox><xmin>314</xmin><xmax>317</xmax><ymin>35</ymin><ymax>36</ymax></bndbox></object><object><name>Word</name><bndbox><xmin>296</xmin><xmax>323</xmax><ymin>48</ymin><ymax>193</ymax></bndbox><text>hallucinations</text></object><bndbox><xmin>296</xmin><xmax>323</xmax><ymin>35</ymin><ymax>193</ymax></bndbox><text>hallucinations</text></object><object><name>TextLine</name><object><name>Symbol</name><bndbox><xmin>347</xmin><xmax>347</xmax><ymin>45</ymin><ymax>46</ymax></bndbox></object><object><name>Word</name><bndbox><xmin>329</xmin><xmax>350</xmax><ymin>60</ymin><ymax>116</ymax></bndbox><text>crowd</text></object><bndbox><xmin>329</xmin><xmax>350</xmax><ymin>45</ymin><ymax>116</ymax></bndbox><text>crowd</text></object><object><name>TextLine</name><object><name>Symbol</name><bndbox><xmin>367</xmin><xmax>368</xmax><ymin>41</ymin><ymax>42</ymax></bndbox></object><object><name>Word</name><bndbox><xmin>365</xmin><xmax>375</xmax><ymin>60</ymin><ymax>105</ymax></bndbox><text>area</text></object><bndbox><xmin>365</xmin><xmax>375</xmax><ymin>41</ymin><ymax>105</ymax></bndbox><text>area</text></object><object><name>TextLine</name><object><name>Symbol</name><bndbox><xmin>405</xmin><xmax>405</xmax><ymin>33</ymin><ymax>34</ymax></bndbox></object><object><name>Word</name><bndbox><xmin>384</xmin><xmax>408</xmax><ymin>48</ymin><ymax>143</ymax></bndbox><text>motion</text></object><bndbox><xmin>384</xmin><xmax>408</xmax><ymin>33</ymin><ymax>143</ymax></bndbox><text>motion</text></object><bndbox><xmin>296</xmin><xmax>408</xmax><ymin>33</ymin><ymax>193</ymax></bndbox></object><object><name>Formula</name><bndbox><xmin>279</xmin><xmax>346</xmax><ymin>273</ymin><ymax>557</ymax></bndbox></object></annotation>