<annotation><filename>090.png</filename><folder>texts</folder><size><height>665</height><width>885</width></size><object><name>Formula</name><bndbox><xmin>837</xmin><xmax>883</xmax><ymin>183</ymin><ymax>547</ymax></bndbox></object><object><name>List</name><object><name>TextLine</name><object><name>Symbol</name><bndbox><xmin>752</xmin><xmax>762</xmax><ymin>268</ymin><ymax>275</ymax></bndbox></object><object><name>Word</name><bndbox><xmin>747</xmin><xmax>768</xmax><ymin>203</ymin><ymax>253</ymax></bndbox><text>place</text></object><bndbox><xmin>747</xmin><xmax>768</xmax><ymin>203</ymin><ymax>275</ymax></bndbox><text>place</text></object><object><name>TextLine</name><object><name>Symbol</name><bndbox><xmin>712</xmin><xmax>721</xmax><ymin>269</ymin><ymax>277</ymax></bndbox></object><object><name>Word</name><bndbox><xmin>706</xmin><xmax>732</xmax><ymin>139</ymin><ymax>257</ymax></bndbox><text>temperature</text></object><bndbox><xmin>706</xmin><xmax>732</xmax><ymin>139</ymin><ymax>277</ymax></bndbox><text>temperature</text></object><object><name>TextLine</name><object><name>Symbol</name><bndbox><xmin>670</xmin><xmax>680</xmax><ymin>267</ymin><ymax>275</ymax></bndbox></object><object><name>Word</name><bndbox><xmin>669</xmin><xmax>682</xmax><ymin>198</ymin><ymax>252</ymax></bndbox><text>sense</text></object><bndbox><xmin>669</xmin><xmax>682</xmax><ymin>198</ymin><ymax>275</ymax></bndbox><text>sense</text></object><bndbox><xmin>669</xmin><xmax>768</xmax><ymin>139</ymin><ymax>277</ymax></bndbox></object><object><name>List</name><object><name>TextLine</name><object><name>Symbol</name><bndbox><xmin>602</xmin><xmax>613</xmax><ymin>624</ymin><ymax>634</ymax></bndbox></object><object><name>Word</name><bndbox><xmin>601</xmin><xmax>622</xmax><ymin>507</ymin><ymax>609</ymax></bndbox><text>movement</text></object><bndbox><xmin>601</xmin><xmax>622</xmax><ymin>507</ymin><ymax>634</ymax></bndbox><text>movement</text></object><object><name>TextLine</name><object><name>Symbol</name><bndbox><xmin>561</xmin><xmax>573</xmax><ymin>627</ymin><ymax>639</ymax></bndbox></object><object><name>Word</name><bndbox><xmin>557</xmin><xmax>581</xmax><ymin>577</ymin><ymax>610</ymax></bndbox><text>fool</text></object><bndbox><xmin>557</xmin><xmax>581</xmax><ymin>577</ymin><ymax>639</ymax></bndbox><text>fool</text></object><object><name>TextLine</name><object><name>Symbol</name><bndbox><xmin>524</xmin><xmax>536</xmax><ymin>626</ymin><ymax>635</ymax></bndbox></object><object><name>Word</name><bndbox><xmin>514</xmin><xmax>540</xmax><ymin>487</ymin><ymax>615</ymax></bndbox><text>employment</text></object><bndbox><xmin>514</xmin><xmax>540</xmax><ymin>487</ymin><ymax>635</ymax></bndbox><text>employment</text></object><object><name>TextLine</name><object><name>Symbol</name><bndbox><xmin>482</xmin><xmax>495</xmax><ymin>625</ymin><ymax>635</ymax></bndbox></object><object><name>Word</name><bndbox><xmin>483</xmin><xmax>497</xmax><ymin>563</ymin><ymax>607</ymax></bndbox><text>times</text></object><bndbox><xmin>482</xmin><xmax>497</xmax><ymin>563</ymin><ymax>635</ymax></bndbox><text>times</text></object><bndbox><xmin>482</xmin><xmax>622</xmax><ymin>487</ymin><ymax>639</ymax></bndbox></object><object><name>Diagram</name><object><name>Drawing</name><bndbox><xmin>376</xmin><xmax>548</xmax><ymin>25</ymin><ymax>372</ymax></bndbox></object><object><name>TextLine</name><object><name>Word</name><bndbox><xmin>494</xmin><xmax>511</xmax><ymin>392</ymin><ymax>433</ymax></bndbox><text>copper</text></object><object><name>Word</name><bndbox><xmin>505</xmin><xmax>523</xmax><ymin>352</ymin><ymax>376</ymax></bndbox><text>tab</text></object><bndbox><xmin>494</xmin><xmax>523</xmax><ymin>352</ymin><ymax>433</ymax></bndbox><text>copper tab</text></object><object><name>Structure</name><text>down</text><bndbox><xmin>497</xmin><xmax>561</xmax><ymin>268</ymin><ymax>276</ymax></bndbox></object><object><name>TextLine</name><object><name>Word</name><bndbox><xmin>565</xmin><xmax>583</xmax><ymin>230</ymin><ymax>283</ymax></bndbox><text>silicon</text></object><object><name>Word</name><bndbox><xmin>568</xmin><xmax>583</xmax><ymin>196</ymin><ymax>222</ymax></bndbox><text>die</text></object><bndbox><xmin>565</xmin><xmax>583</xmax><ymin>196</ymin><ymax>283</ymax></bndbox><text>silicon die</text></object><object><name>Structure</name><text>down</text><bndbox><xmin>523</xmin><xmax>597</xmax><ymin>146</ymin><ymax>156</ymax></bndbox></object><object><name>TextLine</name><object><name>Word</name><bndbox><xmin>605</xmin><xmax>619</xmax><ymin>79</ymin><ymax>171</ymax></bndbox><text>aluminium</text></object><object><name>Word</name><bndbox><xmin>591</xmin><xmax>604</xmax><ymin>91</ymin><ymax>128</ymax></bndbox><text>wires</text></object><bndbox><xmin>591</xmin><xmax>619</xmax><ymin>79</ymin><ymax>171</ymax></bndbox><text>aluminium wires</text></object><object><name>Structure</name><text>down</text><bndbox><xmin>515</xmin><xmax>555</xmax><ymin>26</ymin><ymax>36</ymax></bndbox></object><object><name>TextLine</name><object><name>Word</name><bndbox><xmin>574</xmin><xmax>585</xmax><ymin>26</ymin><ymax>66</ymax></bndbox><text>source</text></object><object><name>Word</name><bndbox><xmin>555</xmin><xmax>567</xmax><ymin>11</ymin><ymax>83</ymax></bndbox><text>connection</text></object><bndbox><xmin>555</xmin><xmax>585</xmax><ymin>11</ymin><ymax>83</ymax></bndbox><text>source connection</text></object><object><name>Structure</name><text>up</text><bndbox><xmin>383</xmin><xmax>411</xmax><ymin>60</ymin><ymax>79</ymax></bndbox></object><object><name>TextLine</name><object><name>Word</name><object><name>Correction</name><bndbox><xmin>353</xmin><xmax>359</xmax><ymin>153</ymin><ymax>186</ymax></bndbox><text>canceling</text></object><bndbox><xmin>353</xmin><xmax>366</xmax><ymin>161</ymin><ymax>183</ymax></bndbox><text>canceling</text></object><object><name>Word</name><bndbox><xmin>354</xmin><xmax>366</xmax><ymin>105</ymin><ymax>135</ymax></bndbox><text>Gate</text></object><object><name>Word</name><bndbox><xmin>355</xmin><xmax>368</xmax><ymin>0</ymin><ymax>86</ymax></bndbox><text>connection</text></object><bndbox><xmin>353</xmin><xmax>368</xmax><ymin>0</ymin><ymax>183</ymax></bndbox><text>canceling Gate connection</text></object><bndbox><xmin>353</xmin><xmax>619</xmax><ymin>0</ymin><ymax>433</ymax></bndbox></object><object><name>TextBlock</name><object><name>TextLine</name><object><name>Word</name><bndbox><xmin>234</xmin><xmax>256</xmax><ymin>612</ymin><ymax>614</ymax></bndbox><text>I</text></object><object><name>Word</name><bndbox><xmin>237</xmin><xmax>250</xmax><ymin>545</ymin><ymax>602</ymax></bndbox><text>mean</text></object><object><name>Word</name><bndbox><xmin>239</xmin><xmax>251</xmax><ymin>485</ymin><ymax>515</ymax></bndbox><text>our</text></object><object><name>Word</name><bndbox><xmin>240</xmin><xmax>261</xmax><ymin>348</ymin><ymax>449</ymax></bndbox><text>children</text></object><object><name>Word</name><bndbox><xmin>248</xmin><xmax>248</xmax><ymin>313</ymin><ymax>314</ymax></bndbox><text>.</text></object><object><name>Word</name><bndbox><xmin>244</xmin><xmax>266</xmax><ymin>262</ymin><ymax>293</ymax></bndbox><text>She</text></object><object><name>Word</name><bndbox><xmin>246</xmin><xmax>267</xmax><ymin>152</ymin><ymax>233</ymax></bndbox><text>sounded</text></object><object><name>Word</name><bndbox><xmin>251</xmin><xmax>260</xmax><ymin>94</ymin><ymax>112</ymax></bndbox><text>as</text></object><object><name>Word</name><object><name>Correction</name><bndbox><xmin>255</xmin><xmax>262</xmax><ymin>7</ymin><ymax>79</ymax></bndbox><text>canceling</text></object><bndbox><xmin>232</xmin><xmax>269</xmax><ymin>2</ymin><ymax>80</ymax></bndbox><text>canceling</text></object><bndbox><xmin>232</xmin><xmax>269</xmax><ymin>2</ymin><ymax>614</ymax></bndbox><text>I mean our children . She sounded as canceling</text></object><object><name>TextLine</name><object><name>Word</name><bndbox><xmin>185</xmin><xmax>213</xmax><ymin>544</ymin><ymax>617</ymax></bndbox><text>though </text></object><object><name>Word</name><bndbox><xmin>199</xmin><xmax>217</xmax><ymin>463</ymin><ymax>506</ymax></bndbox><text>they</text></object><object><name>Word</name><bndbox><xmin>200</xmin><xmax>220</xmax><ymin>353</ymin><ymax>437</ymax></bndbox><text>already</text></object><object><name>Word</name><bndbox><xmin>207</xmin><xmax>227</xmax><ymin>259</ymin><ymax>329</ymax></bndbox><text>existed</text></object><object><name>Word</name><bndbox><xmin>213</xmin><xmax>213</xmax><ymin>243</ymin><ymax>243</ymax></bndbox><text>.</text></object><object><name>Word</name><bndbox><xmin>213</xmin><xmax>225</xmax><ymin>203</ymin><ymax>219</ymax></bndbox><text>In</text></object><object><name>Word</name><bndbox><xmin>203</xmin><xmax>229</xmax><ymin>137</ymin><ymax>176</ymax></bndbox><text>spite</text></object><object><name>Word</name><bndbox><xmin>208</xmin><xmax>229</xmax><ymin>100</ymin><ymax>115</ymax></bndbox><text>of</text></object><bndbox><xmin>185</xmin><xmax>229</xmax><ymin>100</ymin><ymax>617</ymax></bndbox><text>though  they already existed . In spite of</text></object><bndbox><xmin>185</xmin><xmax>269</xmax><ymin>2</ymin><ymax>617</ymax></bndbox></object><object><name>TextBlock</name><object><name>TextLine</name><object><name>Word</name><bndbox><xmin>90</xmin><xmax>101</xmax><ymin>560</ymin><ymax>592</ymax></bndbox><text>the</text></object><object><name>Word</name><bndbox><xmin>90</xmin><xmax>106</xmax><ymin>438</ymin><ymax>534</ymax></bndbox><text>hundred</text></object><object><name>Word</name><bndbox><xmin>81</xmin><xmax>110</xmax><ymin>338</ymin><ymax>407</ymax></bndbox><text>things</text></object><object><name>Word</name><bndbox><xmin>99</xmin><xmax>115</xmax><ymin>282</ymin><ymax>300</ymax></bndbox><text>he</text></object><object><name>Word</name><bndbox><xmin>96</xmin><xmax>113</xmax><ymin>220</ymin><ymax>259</ymax></bndbox><text>had</text></object><object><name>Word</name><bndbox><xmin>97</xmin><xmax>107</xmax><ymin>170</ymin><ymax>192</ymax></bndbox><text>on</text></object><object><name>Word</name><bndbox><xmin>97</xmin><xmax>113</xmax><ymin>123</ymin><ymax>152</ymax></bndbox><text>his</text></object><object><name>Word</name><bndbox><xmin>98</xmin><xmax>113</xmax><ymin>40</ymin><ymax>92</ymax></bndbox><text>mind</text></object><object><name>Word</name><bndbox><xmin>96</xmin><xmax>102</xmax><ymin>26</ymin><ymax>30</ymax></bndbox><text>,</text></object><bndbox><xmin>81</xmin><xmax>115</xmax><ymin>26</ymin><ymax>592</ymax></bndbox><text>the hundred things he had on his mind ,</text></object><object><name>TextLine</name><object><name>Word</name><bndbox><xmin>60</xmin><xmax>76</xmax><ymin>514</ymin><ymax>594</ymax></bndbox><text>Winston</text></object><object><name>Word</name><bndbox><xmin>60</xmin><xmax>73</xmax><ymin>441</ymin><ymax>484</ymax></bndbox><text>went</text></object><object><name>Word</name><bndbox><xmin>61</xmin><xmax>73</xmax><ymin>372</ymin><ymax>409</ymax></bndbox><text>and</text></object><object><name>Word</name><bndbox><xmin>57</xmin><xmax>76</xmax><ymin>308</ymin><ymax>344</ymax></bndbox><text>put</text></object><object><name>Word</name><bndbox><xmin>65</xmin><xmax>77</xmax><ymin>259</ymin><ymax>292</ymax></bndbox><text>his</text></object><object><name>Word</name><object><name>Correction</name><bndbox><xmin>65</xmin><xmax>69</xmax><ymin>184</ymin><ymax>233</ymax></bndbox><text>canceling</text></object><bndbox><xmin>64</xmin><xmax>73</xmax><ymin>183</ymin><ymax>233</ymax></bndbox><text>canceling</text></object><object><name>Word</name><bndbox><xmin>62</xmin><xmax>70</xmax><ymin>123</ymin><ymax>159</ymax></bndbox><text>arm</text></object><object><name>Word</name><bndbox><xmin>62</xmin><xmax>77</xmax><ymin>28</ymin><ymax>106</ymax></bndbox><text>around</text></object><bndbox><xmin>57</xmin><xmax>77</xmax><ymin>28</ymin><ymax>594</ymax></bndbox><text>Winston went and put his canceling arm around</text></object><object><name>TextLine</name><object><name>Word</name><bndbox><xmin>31</xmin><xmax>42</xmax><ymin>574</ymin><ymax>597</ymax></bndbox><text>her</text></object><object><name>Word</name><bndbox><xmin>31</xmin><xmax>45</xmax><ymin>476</ymin><ymax>547</ymax></bndbox><text>waist</text></object><object><name>Word</name><bndbox><xmin>31</xmin><xmax>32</xmax><ymin>459</ymin><ymax>459</ymax></bndbox><text>.</text></object><object><name>Word</name><bndbox><xmin>32</xmin><xmax>48</xmax><ymin>378</ymin><ymax>432</ymax></bndbox><text>We've</text></object><object><name>Word</name><bndbox><xmin>21</xmin><xmax>46</xmax><ymin>331</ymin><ymax>359</ymax></bndbox><text>got</text></object><object><name>Word</name><bndbox><xmin>26</xmin><xmax>46</xmax><ymin>244</ymin><ymax>306</ymax></bndbox><text>plenty</text></object><object><name>Word</name><bndbox><xmin>35</xmin><xmax>49</xmax><ymin>215</ymin><ymax>228</ymax></bndbox><text>of</text></object><object><name>Word</name><bndbox><xmin>32</xmin><xmax>47</xmax><ymin>145</ymin><ymax>190</ymax></bndbox><text>time</text></object><object><name>Word</name><bndbox><xmin>36</xmin><xmax>46</xmax><ymin>101</ymin><ymax>117</ymax></bndbox><text>to</text></object><object><name>Word</name><bndbox><xmin>35</xmin><xmax>48</xmax><ymin>28</ymin><ymax>86</ymax></bndbox><text>think</text></object><bndbox><xmin>21</xmin><xmax>49</xmax><ymin>28</ymin><ymax>597</ymax></bndbox><text>her waist . We've got plenty of time to think</text></object><object><name>TextLine</name><object><name>Word</name><bndbox><xmin>0</xmin><xmax>16</xmax><ymin>538</ymin><ymax>596</ymax></bndbox><text>about</text></object><object><name>Word</name><bndbox><xmin>4</xmin><xmax>18</xmax><ymin>475</ymin><ymax>515</ymax></bndbox><text>that</text></object><object><name>Word</name><bndbox><xmin>7</xmin><xmax>7</xmax><ymin>457</ymin><ymax>458</ymax></bndbox><text>.</text></object><bndbox><xmin>0</xmin><xmax>18</xmax><ymin>457</ymin><ymax>596</ymax></bndbox><text>about that .</text></object><bndbox><xmin>0</xmin><xmax>115</xmax><ymin>26</ymin><ymax>597</ymax></bndbox></object></annotation>