<annotation><folder>texts</folder><size><height>640</height><width>677</width></size><object><name>TextBlock</name><object><name>TextLine</name><object><name>Word</name><bndbox><xmin>648</xmin><xmax>676</xmax><ymin>584</ymin><ymax>638</ymax></bndbox><text>Two</text></object><object><name>Word</name><bndbox><xmin>640</xmin><xmax>673</xmax><ymin>541</ymin><ymax>561</ymax></bndbox><text>of</text></object><object><name>Word</name><bndbox><xmin>649</xmin><xmax>673</xmax><ymin>483</ymin><ymax>519</ymax></bndbox><text>the</text></object><object><name>Word</name><bndbox><xmin>637</xmin><xmax>668</xmax><ymin>396</ymin><ymax>460</ymax></bndbox><text>fluids</text></object><object><name>Word</name><bndbox><xmin>646</xmin><xmax>669</xmax><ymin>291</ymin><ymax>373</ymax></bndbox><text>showed</text></object><object><name>Word</name><bndbox><xmin>650</xmin><xmax>660</xmax><ymin>266</ymin><ymax>274</ymax></bndbox><text>a</text></object><object><name>Word</name><bndbox><xmin>637</xmin><xmax>674</xmax><ymin>94</ymin><ymax>248</ymax></bndbox><text>high-positive</text></object><object><name>Word</name><bndbox><xmin>643</xmin><xmax>663</xmax><ymin>4</ymin><ymax>74</ymax></bndbox><text>normal</text></object><bndbox><xmin>637</xmin><xmax>676</xmax><ymin>4</ymin><ymax>638</ymax></bndbox><text>Two of the fluids showed a high-positive normal</text></object><object><name>TextLine</name><object><name>Word</name><bndbox><xmin>594</xmin><xmax>613</xmax><ymin>537</ymin><ymax>618</ymax></bndbox><text>pressure</text></object><object><name>Word</name><bndbox><xmin>596</xmin><xmax>623</xmax><ymin>473</ymin><ymax>517</ymax></bndbox><text>when</text></object><object><name>Word</name><bndbox><xmin>580</xmin><xmax>614</xmax><ymin>331</ymin><ymax>450</ymax></bndbox><text>undergoing</text></object><object><name>Word</name><bndbox><xmin>594</xmin><xmax>615</xmax><ymin>252</ymin><ymax>309</ymax></bndbox><text>shear</text></object><object><name>Word</name><bndbox><xmin>598</xmin><xmax>599</xmax><ymin>241</ymin><ymax>241</ymax></bndbox><text>,</text></object><object><name>Word</name><bndbox><xmin>592</xmin><xmax>609</xmax><ymin>184</ymin><ymax>223</ymax></bndbox><text>and</text></object><object><name>Word</name><bndbox><xmin>587</xmin><xmax>611</xmax><ymin>131</ymin><ymax>166</ymax></bndbox><text>two</text></object><object><name>Word</name><bndbox><xmin>588</xmin><xmax>610</xmax><ymin>26</ymin><ymax>109</ymax></bndbox><text>showed</text></object><bndbox><xmin>580</xmin><xmax>623</xmax><ymin>26</ymin><ymax>618</ymax></bndbox><text>pressure when undergoing shear , and two showed</text></object><object><name>TextLine</name><object><name>Word</name><bndbox><xmin>549</xmin><xmax>570</xmax><ymin>566</ymin><ymax>626</ymax></bndbox><text>small</text></object><object><name>Word</name><bndbox><xmin>535</xmin><xmax>567</xmax><ymin>455</ymin><ymax>547</ymax></bndbox><text>negative</text></object><object><name>Word</name><bndbox><xmin>533</xmin><xmax>555</xmax><ymin>341</ymin><ymax>435</ymax></bndbox><text>pressures</text></object><object><name>Word</name><bndbox><xmin>540</xmin><xmax>563</xmax><ymin>263</ymin><ymax>324</ymax></bndbox><text>which</text></object><object><name>Word</name><bndbox><xmin>538</xmin><xmax>551</xmax><ymin>185</ymin><ymax>236</ymax></bndbox><text>were</text></object><object><name>Word</name><bndbox><xmin>523</xmin><xmax>556</xmax><ymin>52</ymin><ymax>162</ymax></bndbox><text>negibile</text></object><object><name>Word</name><bndbox><xmin>536</xmin><xmax>561</xmax><ymin>8</ymin><ymax>28</ymax></bndbox><text>in</text></object><bndbox><xmin>523</xmin><xmax>570</xmax><ymin>8</ymin><ymax>626</ymax></bndbox><text>small negative pressures which were negibile in</text></object><object><name>TextLine</name><object><name>Word</name><bndbox><xmin>496</xmin><xmax>522</xmax><ymin>508</ymin><ymax>630</ymax></bndbox><text>comparison</text></object><object><name>Word</name><bndbox><xmin>504</xmin><xmax>527</xmax><ymin>437</ymin><ymax>478</ymax></bndbox><text>with</text></object><object><name>Word</name><bndbox><xmin>505</xmin><xmax>524</xmax><ymin>389</ymin><ymax>417</ymax></bndbox><text>the</text></object><object><name>Word</name><bndbox><xmin>504</xmin><xmax>528</xmax><ymin>280</ymin><ymax>367</ymax></bndbox><text>amount</text></object><object><name>Word</name><bndbox><xmin>500</xmin><xmax>530</xmax><ymin>235</ymin><ymax>255</ymax></bndbox><text>of</text></object><object><name>Word</name><bndbox><xmin>503</xmin><xmax>528</xmax><ymin>186</ymin><ymax>215</ymax></bndbox><text>the</text></object><object><name>Word</name><bndbox><xmin>496</xmin><xmax>520</xmax><ymin>90</ymin><ymax>173</ymax></bndbox><text>positive</text></object><object><name>Word</name><bndbox><xmin>497</xmin><xmax>510</xmax><ymin>1</ymin><ymax>70</ymax></bndbox><text>pressures</text></object><bndbox><xmin>496</xmin><xmax>530</xmax><ymin>1</ymin><ymax>630</ymax></bndbox><text>comparison with the amount of the positive pressures</text></object><object><name>TextLine</name><object><name>Word</name><bndbox><xmin>458</xmin><xmax>482</xmax><ymin>527</ymin><ymax>630</ymax></bndbox><text>generated</text></object><object><name>Word</name><bndbox><xmin>461</xmin><xmax>480</xmax><ymin>483</ymin><ymax>508</ymax></bndbox><text>by</text></object><object><name>Word</name><bndbox><xmin>460</xmin><xmax>478</xmax><ymin>433</ymin><ymax>463</ymax></bndbox><text>the</text></object><object><name>Word</name><bndbox><xmin>458</xmin><xmax>480</xmax><ymin>361</ymin><ymax>410</ymax></bndbox><text>other</text></object><object><name>Word</name><bndbox><xmin>461</xmin><xmax>480</xmax><ymin>302</ymin><ymax>340</ymax></bndbox><text>two</text></object><object><name>Word</name><bndbox><xmin>460</xmin><xmax>461</xmax><ymin>292</ymin><ymax>294</ymax></bndbox><text>.</text></object><bndbox><xmin>458</xmin><xmax>482</xmax><ymin>292</ymin><ymax>630</ymax></bndbox><text>generated by the other two .</text></object><bndbox><xmin>458</xmin><xmax>676</xmax><ymin>1</ymin><ymax>638</ymax></bndbox></object><object><name>List</name><object><name>TextLine</name><object><name>Symbol</name><bndbox><xmin>420</xmin><xmax>425</xmax><ymin>623</ymin><ymax>627</ymax></bndbox></object><object><name>Word</name><bndbox><xmin>409</xmin><xmax>434</xmax><ymin>557</ymin><ymax>609</ymax></bndbox><text>West</text></object><bndbox><xmin>409</xmin><xmax>434</xmax><ymin>557</ymin><ymax>627</ymax></bndbox><text>West</text></object><object><name>TextLine</name><object><name>Symbol</name><bndbox><xmin>384</xmin><xmax>385</xmax><ymin>624</ymin><ymax>626</ymax></bndbox></object><object><name>Word</name><bndbox><xmin>371</xmin><xmax>395</xmax><ymin>517</ymin><ymax>606</ymax></bndbox><text>Question</text></object><bndbox><xmin>371</xmin><xmax>395</xmax><ymin>517</ymin><ymax>626</ymax></bndbox><text>Question</text></object><object><name>TextLine</name><object><name>Symbol</name><bndbox><xmin>344</xmin><xmax>346</xmax><ymin>623</ymin><ymax>624</ymax></bndbox></object><object><name>Word</name><bndbox><xmin>335</xmin><xmax>356</xmax><ymin>481</ymin><ymax>605</ymax></bndbox><text>indications</text></object><bndbox><xmin>335</xmin><xmax>356</xmax><ymin>481</ymin><ymax>624</ymax></bndbox><text>indications</text></object><bndbox><xmin>335</xmin><xmax>434</xmax><ymin>481</ymin><ymax>627</ymax></bndbox></object><object><name>Formula</name><bndbox><xmin>255</xmin><xmax>308</xmax><ymin>302</ymin><ymax>628</ymax></bndbox></object><object><name>Diagram</name><object><name>Drawing</name><bndbox><xmin>9</xmin><xmax>126</xmax><ymin>121</ymin><ymax>577</ymax></bndbox></object><object><name>TextLine</name><object><name>Word</name><bndbox><xmin>65</xmin><xmax>79</xmax><ymin>502</ymin><ymax>518</ymax></bndbox><text>Es</text></object><bndbox><xmin>65</xmin><xmax>79</xmax><ymin>502</ymin><ymax>518</ymax></bndbox><text>Es</text></object><object><name>Structure</name><text>up</text><bndbox><xmin>82</xmin><xmax>109</xmax><ymin>506</ymin><ymax>512</ymax></bndbox></object><object><name>Structure</name><text>down</text><bndbox><xmin>35</xmin><xmax>63</xmax><ymin>506</ymin><ymax>513</ymax></bndbox></object><object><name>TextLine</name><object><name>Word</name><bndbox><xmin>114</xmin><xmax>133</xmax><ymin>449</ymin><ymax>476</ymax></bndbox><text>T1</text></object><bndbox><xmin>114</xmin><xmax>133</xmax><ymin>449</ymin><ymax>476</ymax></bndbox><text>T1</text></object><object><name>TextLine</name><object><name>Word</name><bndbox><xmin>3</xmin><xmax>20</xmax><ymin>462</ymin><ymax>481</ymax></bndbox><text>N1</text></object><object><name>Word</name><bndbox><xmin>7</xmin><xmax>15</xmax><ymin>455</ymin><ymax>457</ymax></bndbox><text>:</text></object><object><name>Word</name><bndbox><xmin>1</xmin><xmax>19</xmax><ymin>431</ymin><ymax>450</ymax></bndbox><text>N2</text></object><bndbox><xmin>1</xmin><xmax>20</xmax><ymin>431</ymin><ymax>481</ymax></bndbox><text>N1 : N2</text></object><object><name>TextLine</name><object><name>Word</name><bndbox><xmin>62</xmin><xmax>74</xmax><ymin>398</ymin><ymax>410</ymax></bndbox><text>Ei</text></object><bndbox><xmin>62</xmin><xmax>74</xmax><ymin>398</ymin><ymax>410</ymax></bndbox><text>Ei</text></object><object><name>Structure</name><text>up</text><bndbox><xmin>80</xmin><xmax>106</xmax><ymin>401</ymin><ymax>406</ymax></bndbox></object><object><name>Structure</name><text>down</text><bndbox><xmin>28</xmin><xmax>58</xmax><ymin>404</ymin><ymax>408</ymax></bndbox></object><object><name>TextLine</name><object><name>Word</name><bndbox><xmin>135</xmin><xmax>151</xmax><ymin>301</ymin><ymax>318</ymax></bndbox><text>Le</text></object><bndbox><xmin>135</xmin><xmax>151</xmax><ymin>301</ymin><ymax>318</ymax></bndbox><text>Le</text></object><object><name>TextLine</name><object><name>Word</name><bndbox><xmin>131</xmin><xmax>148</xmax><ymin>183</ymin><ymax>198</ymax></bndbox><text>Le</text></object><bndbox><xmin>131</xmin><xmax>148</xmax><ymin>183</ymin><ymax>198</ymax></bndbox><text>Le</text></object><object><name>TextLine</name><object><name>Word</name><bndbox><xmin>51</xmin><xmax>67</xmax><ymin>230</ymin><ymax>248</ymax></bndbox><text>M</text></object><bndbox><xmin>51</xmin><xmax>67</xmax><ymin>230</ymin><ymax>248</ymax></bndbox><text>M</text></object><object><name>Structure</name><text>up</text><bndbox><xmin>70</xmin><xmax>105</xmax><ymin>123</ymin><ymax>129</ymax></bndbox></object><object><name>Structure</name><text>down</text><bndbox><xmin>19</xmin><xmax>48</xmax><ymin>125</ymin><ymax>131</ymax></bndbox></object><object><name>TextLine</name><object><name>Word</name><bndbox><xmin>52</xmin><xmax>66</xmax><ymin>108</ymin><ymax>130</ymax></bndbox><text>EO</text></object><bndbox><xmin>52</xmin><xmax>66</xmax><ymin>108</ymin><ymax>130</ymax></bndbox><text>EO</text></object><bndbox><xmin>1</xmin><xmax>151</xmax><ymin>108</ymin><ymax>577</ymax></bndbox></object></annotation>