<annotation><filename>560.png</filename><folder>texts</folder><size><height>642</height><width>846</width></size><object><name>Diagram</name><object><name>Drawing</name><bndbox><xmin>0</xmin><xmax>177</xmax><ymin>32</ymin><ymax>620</ymax></bndbox></object><object><name>TextLine</name><object><name>Word</name><bndbox><xmin>25</xmin><xmax>38</xmax><ymin>132</ymin><ymax>152</ymax></bndbox><text>Cr</text></object><bndbox><xmin>25</xmin><xmax>38</xmax><ymin>132</ymin><ymax>152</ymax></bndbox><text>Cr</text></object><object><name>TextLine</name><object><name>Word</name><bndbox><xmin>47</xmin><xmax>54</xmax><ymin>148</ymin><ymax>149</ymax></bndbox><text>r</text></object><bndbox><xmin>47</xmin><xmax>54</xmax><ymin>148</ymin><ymax>149</ymax></bndbox><text>r</text></object><object><name>TextLine</name><object><name>Word</name><bndbox><xmin>3</xmin><xmax>18</xmax><ymin>231</ymin><ymax>233</ymax></bndbox><text>1</text></object><bndbox><xmin>3</xmin><xmax>18</xmax><ymin>231</ymin><ymax>233</ymax></bndbox><text>1</text></object><object><name>TextLine</name><object><name>Word</name><bndbox><xmin>23</xmin><xmax>37</xmax><ymin>293</ymin><ymax>300</ymax></bndbox><text>2</text></object><bndbox><xmin>23</xmin><xmax>37</xmax><ymin>293</ymin><ymax>300</ymax></bndbox><text>2</text></object><object><name>TextLine</name><object><name>Word</name><bndbox><xmin>38</xmin><xmax>49</xmax><ymin>413</ymin><ymax>423</ymax></bndbox><text>3</text></object><bndbox><xmin>38</xmin><xmax>49</xmax><ymin>413</ymin><ymax>423</ymax></bndbox><text>3</text></object><object><name>TextLine</name><object><name>Word</name><bndbox><xmin>47</xmin><xmax>56</xmax><ymin>568</ymin><ymax>582</ymax></bndbox><text>4</text></object><bndbox><xmin>47</xmin><xmax>56</xmax><ymin>568</ymin><ymax>582</ymax></bndbox><text>4</text></object><bndbox><xmin>0</xmin><xmax>177</xmax><ymin>32</ymin><ymax>620</ymax></bndbox></object><object><name>Table</name><object><name>TextLine</name><object><name>Word</name><bndbox><xmin>215</xmin><xmax>250</xmax><ymin>17</ymin><ymax>237</ymax></bndbox><text>knowledge</text></object><bndbox><xmin>215</xmin><xmax>250</xmax><ymin>17</ymin><ymax>237</ymax></bndbox><text>knowledge</text></object><object><name>TextLine</name><object><name>Word</name><bndbox><xmin>262</xmin><xmax>288</xmax><ymin>12</ymin><ymax>190</ymax></bndbox><text>exchange</text></object><bndbox><xmin>262</xmin><xmax>288</xmax><ymin>12</ymin><ymax>190</ymax></bndbox><text>exchange</text></object><object><name>TextLine</name><object><name>Word</name><bndbox><xmin>313</xmin><xmax>333</xmax><ymin>22</ymin><ymax>144</ymax></bndbox><text>season</text></object><bndbox><xmin>313</xmin><xmax>333</xmax><ymin>22</ymin><ymax>144</ymax></bndbox><text>season</text></object><object><name>TextLine</name><object><name>Word</name><bndbox><xmin>352</xmin><xmax>377</xmax><ymin>14</ymin><ymax>135</ymax></bndbox><text>horses</text></object><bndbox><xmin>352</xmin><xmax>377</xmax><ymin>14</ymin><ymax>135</ymax></bndbox><text>horses</text></object><object><name>TextLine</name><object><name>Word</name><bndbox><xmin>393</xmin><xmax>422</xmax><ymin>14</ymin><ymax>221</ymax></bndbox><text>Dreadnought</text></object><bndbox><xmin>393</xmin><xmax>422</xmax><ymin>14</ymin><ymax>221</ymax></bndbox><text>Dreadnought</text></object><object><name>TextLine</name><object><name>Word</name><bndbox><xmin>447</xmin><xmax>469</xmax><ymin>24</ymin><ymax>97</ymax></bndbox><text>river</text></object><bndbox><xmin>447</xmin><xmax>469</xmax><ymin>24</ymin><ymax>97</ymax></bndbox><text>river</text></object><object><name>TextLine</name><object><name>Word</name><bndbox><xmin>212</xmin><xmax>242</xmax><ymin>369</ymin><ymax>536</ymax></bndbox><text>operations</text></object><bndbox><xmin>212</xmin><xmax>242</xmax><ymin>369</ymin><ymax>536</ymax></bndbox><text>operations</text></object><object><name>TextLine</name><object><name>Word</name><bndbox><xmin>254</xmin><xmax>272</xmax><ymin>420</ymin><ymax>488</ymax></bndbox><text>949</text></object><bndbox><xmin>254</xmin><xmax>272</xmax><ymin>420</ymin><ymax>488</ymax></bndbox><text>949</text></object><object><name>TextLine</name><object><name>Word</name><bndbox><xmin>297</xmin><xmax>314</xmax><ymin>425</ymin><ymax>507</ymax></bndbox><text>593</text></object><bndbox><xmin>297</xmin><xmax>314</xmax><ymin>425</ymin><ymax>507</ymax></bndbox><text>593</text></object><object><name>TextLine</name><object><name>Word</name><bndbox><xmin>340</xmin><xmax>360</xmax><ymin>425</ymin><ymax>480</ymax></bndbox><text>37</text></object><bndbox><xmin>340</xmin><xmax>360</xmax><ymin>425</ymin><ymax>480</ymax></bndbox><text>37</text></object><object><name>TextLine</name><object><name>Word</name><bndbox><xmin>381</xmin><xmax>405</xmax><ymin>423</ymin><ymax>503</ymax></bndbox><text>272</text></object><bndbox><xmin>381</xmin><xmax>405</xmax><ymin>423</ymin><ymax>503</ymax></bndbox><text>272</text></object><object><name>TextLine</name><object><name>Word</name><bndbox><xmin>438</xmin><xmax>465</xmax><ymin>444</ymin><ymax>466</ymax></bndbox><text>9</text></object><bndbox><xmin>438</xmin><xmax>465</xmax><ymin>444</ymin><ymax>466</ymax></bndbox><text>9</text></object><object><name>Structure</name><text>separating line</text><bndbox><xmin>249</xmin><xmax>258</xmax><ymin>7</ymin><ymax>519</ymax></bndbox></object><object><name>Structure</name><text>separating line</text><bndbox><xmin>286</xmin><xmax>299</xmax><ymin>0</ymin><ymax>545</ymax></bndbox></object><object><name>Structure</name><text>separating line</text><bndbox><xmin>332</xmin><xmax>341</xmax><ymin>10</ymin><ymax>533</ymax></bndbox></object><object><name>Structure</name><text>separating line</text><bndbox><xmin>376</xmin><xmax>386</xmax><ymin>12</ymin><ymax>491</ymax></bndbox></object><object><name>Structure</name><text>separating line</text><bndbox><xmin>420</xmin><xmax>430</xmax><ymin>2</ymin><ymax>535</ymax></bndbox></object><object><name>Structure</name><text>separating line</text><bndbox><xmin>476</xmin><xmax>482</xmax><ymin>24</ymin><ymax>538</ymax></bndbox></object><bndbox><xmin>212</xmin><xmax>482</xmax><ymin>0</ymin><ymax>545</ymax></bndbox></object><object><name>TextBlock</name><object><name>TextLine</name><object><name>Word</name><bndbox><xmin>531</xmin><xmax>553</xmax><ymin>6</ymin><ymax>52</ymax></bndbox><text>The</text></object><object><name>Word</name><bndbox><xmin>533</xmin><xmax>556</xmax><ymin>82</ymin><ymax>148</ymax></bndbox><text>other</text></object><object><name>Word</name><bndbox><xmin>536</xmin><xmax>557</xmax><ymin>191</ymin><ymax>276</ymax></bndbox><text>patrons</text></object><object><name>Word</name><bndbox><xmin>539</xmin><xmax>551</xmax><ymin>307</ymin><ymax>358</ymax></bndbox><text>were</text></object><object><name>Word</name><bndbox><xmin>529</xmin><xmax>548</xmax><ymin>383</ymin><ymax>430</ymax></bndbox><text>taxi</text></object><object><name>Word</name><bndbox><xmin>529</xmin><xmax>550</xmax><ymin>456</ymin><ymax>549</ymax></bndbox><text>drivers</text></object><object><name>Word</name><bndbox><xmin>534</xmin><xmax>552</xmax><ymin>572</ymin><ymax>617</ymax></bndbox><text>and</text></object><bndbox><xmin>529</xmin><xmax>557</xmax><ymin>6</ymin><ymax>617</ymax></bndbox><text>The other patrons were taxi drivers and</text></object><object><name>TextLine</name><object><name>Word</name><bndbox><xmin>572</xmin><xmax>591</xmax><ymin>14</ymin><ymax>54</ymax></bndbox><text>art</text></object><object><name>Word</name><bndbox><xmin>571</xmin><xmax>591</xmax><ymin>82</ymin><ymax>191</ymax></bndbox><text>students</text></object><object><name>Word</name><bndbox><xmin>570</xmin><xmax>588</xmax><ymin>207</ymin><ymax>249</ymax></bndbox><text>and</text></object><object><name>Word</name><bndbox><xmin>573</xmin><xmax>586</xmax><ymin>273</ymin><ymax>352</ymax></bndbox><text>small</text></object><object><name>Word</name><bndbox><xmin>569</xmin><xmax>595</xmax><ymin>396</ymin><ymax>549</ymax></bndbox><text>shopkeepers</text></object><object><name>Word</name><bndbox><xmin>588</xmin><xmax>590</xmax><ymin>557</ymin><ymax>559</ymax></bndbox><text>.</text></object><object><name>Word</name><bndbox><xmin>572</xmin><xmax>591</xmax><ymin>564</ymin><ymax>609</ymax></bndbox><text>The</text></object><bndbox><xmin>569</xmin><xmax>595</xmax><ymin>14</ymin><ymax>609</ymax></bndbox><text>art students and small shopkeepers . The</text></object><object><name>TextLine</name><object><name>Word</name><bndbox><xmin>614</xmin><xmax>634</xmax><ymin>21</ymin><ymax>124</ymax></bndbox><text>reporters</text></object><object><name>Word</name><bndbox><xmin>608</xmin><xmax>629</xmax><ymin>150</ymin><ymax>191</ymax></bndbox><text>had</text></object><object><name>Word</name><bndbox><xmin>607</xmin><xmax>627</xmax><ymin>210</ymin><ymax>242</ymax></bndbox><text>not</text></object><object><name>Word</name><bndbox><xmin>613</xmin><xmax>635</xmax><ymin>272</ymin><ymax>310</ymax></bndbox><text>yet</text></object><object><name>Word</name><bndbox><xmin>612</xmin><xmax>631</xmax><ymin>344</ymin><ymax>483</ymax></bndbox><text>discovered</text></object><object><name>Word</name><bndbox><xmin>612</xmin><xmax>633</xmax><ymin>508</ymin><ymax>577</ymax></bndbox><text>that</text></object><bndbox><xmin>607</xmin><xmax>635</xmax><ymin>21</ymin><ymax>577</ymax></bndbox><text>reporters had not yet discovered that</text></object><object><name>TextLine</name><object><name>Word</name><bndbox><xmin>646</xmin><xmax>665</xmax><ymin>17</ymin><ymax>68</ymax></bndbox><text>this</text></object><object><name>Word</name><bndbox><xmin>656</xmin><xmax>668</xmax><ymin>92</ymin><ymax>138</ymax></bndbox><text>was</text></object><object><name>Word</name><bndbox><xmin>650</xmin><xmax>665</xmax><ymin>166</ymin><ymax>209</ymax></bndbox><text>his</text></object><object><name>Word</name><bndbox><xmin>648</xmin><xmax>676</xmax><ymin>233</ymin><ymax>368</ymax></bndbox><text>hideaway</text></object><object><name>Word</name><bndbox><xmin>668</xmin><xmax>671</xmax><ymin>370</ymin><ymax>374</ymax></bndbox><text>.</text></object><object><name>Word</name><bndbox><xmin>656</xmin><xmax>672</xmax><ymin>383</ymin><ymax>424</ymax></bndbox><text>His</text></object><object><name>Word</name><bndbox><xmin>655</xmin><xmax>676</xmax><ymin>447</ymin><ymax>519</ymax></bndbox><text>friend</text></object><object><name>Word</name><bndbox><xmin>657</xmin><xmax>680</xmax><ymin>542</ymin><ymax>600</ymax></bndbox><text>Jane</text></object><bndbox><xmin>646</xmin><xmax>680</xmax><ymin>17</ymin><ymax>600</ymax></bndbox><text>this was his hideaway . His friend Jane</text></object><object><name>TextLine</name><object><name>Word</name><bndbox><xmin>690</xmin><xmax>705</xmax><ymin>12</ymin><ymax>68</ymax></bndbox><text>was</text></object><object><name>Word</name><bndbox><xmin>688</xmin><xmax>705</xmax><ymin>89</ymin><ymax>148</ymax></bndbox><text>with</text></object><object><name>Word</name><bndbox><xmin>681</xmin><xmax>700</xmax><ymin>173</ymin><ymax>222</ymax></bndbox><text>him</text></object><object><name>Word</name><bndbox><xmin>698</xmin><xmax>699</xmax><ymin>234</ymin><ymax>236</ymax></bndbox><text>.</text></object><object><name>Word</name><bndbox><xmin>684</xmin><xmax>702</xmax><ymin>255</ymin><ymax>293</ymax></bndbox><text>She</text></object><object><name>Word</name><bndbox><xmin>691</xmin><xmax>702</xmax><ymin>316</ymin><ymax>358</ymax></bndbox><text>was</text></object><object><name>Word</name><bndbox><xmin>692</xmin><xmax>710</xmax><ymin>379</ymin><ymax>443</ymax></bndbox><text>wise</text></object><object><name>Word</name><bndbox><xmin>696</xmin><xmax>717</xmax><ymin>471</ymin><ymax>558</ymax></bndbox><text>enough</text></object><object><name>Word</name><bndbox><xmin>692</xmin><xmax>716</xmax><ymin>576</ymin><ymax>608</ymax></bndbox><text>to</text></object><bndbox><xmin>681</xmin><xmax>717</xmax><ymin>12</ymin><ymax>608</ymax></bndbox><text>was with him . She was wise enough to</text></object><object><name>TextLine</name><object><name>Word</name><bndbox><xmin>727</xmin><xmax>744</xmax><ymin>26</ymin><ymax>118</ymax></bndbox><text>realise</text></object><object><name>Word</name><bndbox><xmin>730</xmin><xmax>741</xmax><ymin>141</ymin><ymax>151</ymax></bndbox><text>a</text></object><object><name>Word</name><bndbox><xmin>733</xmin><xmax>742</xmax><ymin>181</ymin><ymax>241</ymax></bndbox><text>man</text></object><object><name>Word</name><bndbox><xmin>725</xmin><xmax>741</xmax><ymin>269</ymin><ymax>342</ymax></bndbox><text>could</text></object><object><name>Word</name><bndbox><xmin>725</xmin><xmax>743</xmax><ymin>380</ymin><ymax>408</ymax></bndbox><text>be</text></object><object><name>Word</name><bndbox><xmin>727</xmin><xmax>749</xmax><ymin>436</ymin><ymax>510</ymax></bndbox><text>good</text></object><object><name>Word</name><bndbox><xmin>737</xmin><xmax>760</xmax><ymin>539</ymin><ymax>624</ymax></bndbox><text>Company</text></object><bndbox><xmin>725</xmin><xmax>760</xmax><ymin>26</ymin><ymax>624</ymax></bndbox><text>realise a man could be good Company</text></object><object><name>TextLine</name><object><name>Word</name><bndbox><xmin>768</xmin><xmax>782</xmax><ymin>38</ymin><ymax>86</ymax></bndbox><text>even</text></object><object><name>Word</name><bndbox><xmin>763</xmin><xmax>777</xmax><ymin>109</ymin><ymax>120</ymax></bndbox><text>if</text></object><object><name>Word</name><object><name>Correction</name><bndbox><xmin>761</xmin><xmax>771</xmax><ymin>145</ymin><ymax>188</ymax></bndbox><text>canceling</text></object><bndbox><xmin>761</xmin><xmax>774</xmax><ymin>150</ymin><ymax>191</ymax></bndbox><text>canceling</text></object><object><name>Word</name><bndbox><xmin>759</xmin><xmax>775</xmax><ymin>221</ymin><ymax>249</ymax></bndbox><text>he</text></object><object><name>Word</name><bndbox><xmin>763</xmin><xmax>778</xmax><ymin>276</ymin><ymax>326</ymax></bndbox><text>did</text></object><object><name>Word</name><bndbox><xmin>763</xmin><xmax>784</xmax><ymin>353</ymin><ymax>421</ymax></bndbox><text>weigh</text></object><object><name>Word</name><bndbox><xmin>764</xmin><xmax>780</xmax><ymin>443</ymin><ymax>483</ymax></bndbox><text>too</text></object><object><name>Word</name><bndbox><xmin>767</xmin><xmax>782</xmax><ymin>494</ymin><ymax>571</ymax></bndbox><text>much</text></object><bndbox><xmin>759</xmin><xmax>784</xmax><ymin>38</ymin><ymax>571</ymax></bndbox><text>even if canceling he did weigh too much</text></object><object><name>TextLine</name><object><name>Word</name><bndbox><xmin>797</xmin><xmax>815</xmax><ymin>73</ymin><ymax>117</ymax></bndbox><text>and</text></object><object><name>Word</name><bndbox><xmin>788</xmin><xmax>814</xmax><ymin>158</ymin><ymax>251</ymax></bndbox><text>didn't</text></object><object><name>Word</name><bndbox><xmin>800</xmin><xmax>809</xmax><ymin>286</ymin><ymax>337</ymax></bndbox><text>own</text></object><object><name>Word</name><bndbox><xmin>793</xmin><xmax>810</xmax><ymin>365</ymin><ymax>414</ymax></bndbox><text>the</text></object><object><name>Word</name><bndbox><xmin>796</xmin><xmax>811</xmax><ymin>445</ymin><ymax>516</ymax></bndbox><text>mint</text></object><object><name>Word</name><bndbox><xmin>811</xmin><xmax>812</xmax><ymin>535</ymin><ymax>535</ymax></bndbox><text>.</text></object><bndbox><xmin>788</xmin><xmax>815</xmax><ymin>73</ymin><ymax>535</ymax></bndbox><text>and didn't own the mint .</text></object><bndbox><xmin>529</xmin><xmax>815</xmax><ymin>6</ymin><ymax>624</ymax></bndbox></object></annotation>