<annotation><filename>567.png</filename><folder>texts</folder><size><height>674</height><width>948</width></size><object><name>Drawing</name><bndbox><xmin>720</xmin><xmax>946</xmax><ymin>248</ymin><ymax>615</ymax></bndbox></object><object><name>Diagram</name><object><name>Drawing</name><bndbox><xmin>0</xmin><xmax>194</xmax><ymin>32</ymin><ymax>650</ymax></bndbox></object><object><name>TextLine</name><object><name>Word</name><bndbox><xmin>94</xmin><xmax>111</xmax><ymin>637</ymin><ymax>672</ymax></bndbox><text>Eo</text></object><bndbox><xmin>94</xmin><xmax>111</xmax><ymin>637</ymin><ymax>672</ymax></bndbox><text>Eo</text></object><object><name>Structure</name><text>down</text><bndbox><xmin>117</xmin><xmax>189</xmax><ymin>636</ymin><ymax>649</ymax></bndbox></object><object><name>Structure</name><text>up</text><bndbox><xmin>19</xmin><xmax>88</xmax><ymin>630</ymin><ymax>649</ymax></bndbox></object><object><name>TextLine</name><object><name>Word</name><bndbox><xmin>94</xmin><xmax>112</xmax><ymin>532</ymin><ymax>556</ymax></bndbox><text>m</text></object><bndbox><xmin>94</xmin><xmax>112</xmax><ymin>532</ymin><ymax>556</ymax></bndbox><text>m</text></object><object><name>TextLine</name><object><name>Word</name><bndbox><xmin>78</xmin><xmax>104</xmax><ymin>342</ymin><ymax>367</ymax></bndbox><text>Ei</text></object><bndbox><xmin>78</xmin><xmax>104</xmax><ymin>342</ymin><ymax>367</ymax></bndbox><text>Ei</text></object><object><name>Structure</name><text>up</text><bndbox><xmin>13</xmin><xmax>75</xmax><ymin>348</ymin><ymax>366</ymax></bndbox></object><object><name>Structure</name><text>down</text><bndbox><xmin>102</xmin><xmax>187</xmax><ymin>346</ymin><ymax>370</ymax></bndbox></object><object><name>TextLine</name><object><name>Word</name><bndbox><xmin>68</xmin><xmax>93</xmax><ymin>171</ymin><ymax>202</ymax></bndbox><text>Es</text></object><bndbox><xmin>68</xmin><xmax>93</xmax><ymin>171</ymin><ymax>202</ymax></bndbox><text>Es</text></object><object><name>Structure</name><text>down</text><bndbox><xmin>95</xmin><xmax>165</xmax><ymin>178</ymin><ymax>195</ymax></bndbox></object><object><name>Structure</name><text>up</text><bndbox><xmin>13</xmin><xmax>65</xmax><ymin>179</ymin><ymax>199</ymax></bndbox></object><bndbox><xmin>0</xmin><xmax>194</xmax><ymin>32</ymin><ymax>672</ymax></bndbox></object><object><name>Table</name><object><name>TextLine</name><object><name>Word</name><bndbox><xmin>727</xmin><xmax>749</xmax><ymin>3</ymin><ymax>80</ymax></bndbox><text>activity</text></object><bndbox><xmin>727</xmin><xmax>749</xmax><ymin>3</ymin><ymax>80</ymax></bndbox><text>activity</text></object><object><name>TextLine</name><object><name>Word</name><bndbox><xmin>725</xmin><xmax>751</xmax><ymin>136</ymin><ymax>185</ymax></bndbox><text>point</text></object><bndbox><xmin>725</xmin><xmax>751</xmax><ymin>136</ymin><ymax>185</ymax></bndbox><text>point</text></object><object><name>TextLine</name><object><name>Word</name><bndbox><xmin>758</xmin><xmax>779</xmax><ymin>145</ymin><ymax>192</ymax></bndbox><text>580</text></object><bndbox><xmin>758</xmin><xmax>779</xmax><ymin>145</ymin><ymax>192</ymax></bndbox><text>580</text></object><object><name>TextLine</name><object><name>Word</name><bndbox><xmin>794</xmin><xmax>813</xmax><ymin>147</ymin><ymax>171</ymax></bndbox><text>81</text></object><bndbox><xmin>794</xmin><xmax>813</xmax><ymin>147</ymin><ymax>171</ymax></bndbox><text>81</text></object><object><name>TextLine</name><object><name>Word</name><bndbox><xmin>833</xmin><xmax>856</xmax><ymin>133</ymin><ymax>179</ymax></bndbox><text>732</text></object><bndbox><xmin>833</xmin><xmax>856</xmax><ymin>133</ymin><ymax>179</ymax></bndbox><text>732</text></object><object><name>TextLine</name><object><name>Word</name><bndbox><xmin>755</xmin><xmax>776</xmax><ymin>0</ymin><ymax>108</ymax></bndbox><text>judgements</text></object><bndbox><xmin>755</xmin><xmax>776</xmax><ymin>0</ymin><ymax>108</ymax></bndbox><text>judgements</text></object><object><name>TextLine</name><object><name>Word</name><bndbox><xmin>792</xmin><xmax>812</xmax><ymin>5</ymin><ymax>84</ymax></bndbox><text>energies</text></object><bndbox><xmin>792</xmin><xmax>812</xmax><ymin>5</ymin><ymax>84</ymax></bndbox><text>energies</text></object><object><name>TextLine</name><object><name>Word</name><bndbox><xmin>832</xmin><xmax>847</xmax><ymin>9</ymin><ymax>78</ymax></bndbox><text>trees</text></object><bndbox><xmin>832</xmin><xmax>847</xmax><ymin>9</ymin><ymax>78</ymax></bndbox><text>trees</text></object><object><name>Structure</name><text>separating line</text><bndbox><xmin>748</xmin><xmax>756</xmax><ymin>1</ymin><ymax>187</ymax></bndbox></object><object><name>Structure</name><text>separating line</text><bndbox><xmin>783</xmin><xmax>787</xmax><ymin>10</ymin><ymax>184</ymax></bndbox></object><object><name>Structure</name><text>separating line</text><bndbox><xmin>814</xmin><xmax>816</xmax><ymin>10</ymin><ymax>175</ymax></bndbox></object><object><name>Structure</name><text>separating line</text><bndbox><xmin>862</xmin><xmax>868</xmax><ymin>28</ymin><ymax>180</ymax></bndbox></object><bndbox><xmin>725</xmin><xmax>868</xmax><ymin>0</ymin><ymax>192</ymax></bndbox></object><object><name>TextBlock</name><object><name>TextLine</name><object><name>Word</name><bndbox><xmin>227</xmin><xmax>246</xmax><ymin>12</ymin><ymax>74</ymax></bndbox><text>Weld</text></object><object><name>Word</name><bndbox><xmin>232</xmin><xmax>249</xmax><ymin>105</ymin><ymax>155</ymax></bndbox><text>was</text></object><object><name>Word</name><bndbox><xmin>229</xmin><xmax>246</xmax><ymin>175</ymin><ymax>219</ymax></bndbox><text>the</text></object><object><name>Word</name><bndbox><xmin>234</xmin><xmax>246</xmax><ymin>249</ymin><ymax>291</ymax></bndbox><text>son</text></object><object><name>Word</name><bndbox><xmin>235</xmin><xmax>249</xmax><ymin>315</ymin><ymax>355</ymax></bndbox><text>and</text></object><object><name>Word</name><bndbox><xmin>235</xmin><xmax>260</xmax><ymin>377</ymin><ymax>498</ymax></bndbox><text>grandson</text></object><object><name>Word</name><bndbox><xmin>233</xmin><xmax>254</xmax><ymin>523</ymin><ymax>552</ymax></bndbox><text>of</text></object><object><name>Word</name><bndbox><xmin>236</xmin><xmax>248</xmax><ymin>571</ymin><ymax>643</ymax></bndbox><text>New</text></object><bndbox><xmin>227</xmin><xmax>260</xmax><ymin>12</ymin><ymax>643</ymax></bndbox><text>Weld was the son and grandson of New</text></object><object><name>TextLine</name><object><name>Word</name><bndbox><xmin>265</xmin><xmax>289</xmax><ymin>38</ymin><ymax>128</ymax></bndbox><text>England</text></object><object><name>Word</name><bndbox><xmin>266</xmin><xmax>294</xmax><ymin>161</ymin><ymax>348</ymax></bndbox><text>Congregational</text></object><object><name>Word</name><bndbox><xmin>272</xmin><xmax>286</xmax><ymin>376</ymin><ymax>510</ymax></bndbox><text>ministers</text></object><object><name>Word</name><bndbox><xmin>285</xmin><xmax>287</xmax><ymin>517</ymin><ymax>518</ymax></bndbox><text>.</text></object><object><name>Word</name><bndbox><xmin>272</xmin><xmax>288</xmax><ymin>537</ymin><ymax>567</ymax></bndbox><text>As</text></object><object><name>Word</name><bndbox><xmin>277</xmin><xmax>287</xmax><ymin>596</ymin><ymax>612</ymax></bndbox><text>a</text></object><bndbox><xmin>265</xmin><xmax>294</xmax><ymin>38</ymin><ymax>612</ymax></bndbox><text>England Congregational ministers . As a</text></object><object><name>TextLine</name><object><name>Word</name><bndbox><xmin>307</xmin><xmax>330</xmax><ymin>43</ymin><ymax>133</ymax></bndbox><text>youth</text></object><object><name>Word</name><bndbox><xmin>302</xmin><xmax>321</xmax><ymin>162</ymin><ymax>188</ymax></bndbox><text>he</text></object><object><name>Word</name><bndbox><xmin>304</xmin><xmax>323</xmax><ymin>223</ymin><ymax>326</ymax></bndbox><text>became</text></object><object><name>Word</name><bndbox><xmin>314</xmin><xmax>326</xmax><ymin>366</ymin><ymax>417</ymax></bndbox><text>one</text></object><object><name>Word</name><bndbox><xmin>305</xmin><xmax>322</xmax><ymin>445</ymin><ymax>471</ymax></bndbox><text>of</text></object><object><name>Word</name><bndbox><xmin>305</xmin><xmax>334</xmax><ymin>507</ymin><ymax>632</ymax></bndbox><text>Finney's</text></object><bndbox><xmin>302</xmin><xmax>334</xmax><ymin>43</ymin><ymax>632</ymax></bndbox><text>youth he became one of Finney's</text></object><object><name>TextLine</name><object><name>Word</name><bndbox><xmin>342</xmin><xmax>365</xmax><ymin>55</ymin><ymax>127</ymax></bndbox><text>band</text></object><object><name>Word</name><bndbox><xmin>341</xmin><xmax>359</xmax><ymin>158</ymin><ymax>182</ymax></bndbox><text>of</text></object><object><name>Word</name><bndbox><xmin>344</xmin><xmax>366</xmax><ymin>210</ymin><ymax>366</ymax></bndbox><text>evangelists</text></object><object><name>Word</name><bndbox><xmin>342</xmin><xmax>362</xmax><ymin>387</ymin><ymax>431</ymax></bndbox><text>and</text></object><object><name>Word</name><bndbox><xmin>350</xmin><xmax>368</xmax><ymin>450</ymin><ymax>512</ymax></bndbox><text>gave</text></object><object><name>Word</name><bndbox><xmin>342</xmin><xmax>360</xmax><ymin>535</ymin><ymax>636</ymax></bndbox><text>himself</text></object><bndbox><xmin>341</xmin><xmax>368</xmax><ymin>55</ymin><ymax>636</ymax></bndbox><text>band of evangelists and gave himself</text></object><object><name>TextLine</name><object><name>Word</name><bndbox><xmin>378</xmin><xmax>400</xmax><ymin>67</ymin><ymax>91</ymax></bndbox><text>to</text></object><object><name>Word</name><bndbox><xmin>383</xmin><xmax>405</xmax><ymin>111</ymin><ymax>214</ymax></bndbox><text>winning</text></object><object><name>Word</name><bndbox><xmin>391</xmin><xmax>408</xmax><ymin>237</ymin><ymax>320</ymax></bndbox><text>young</text></object><object><name>Word</name><bndbox><xmin>394</xmin><xmax>404</xmax><ymin>348</ymin><ymax>401</ymax></bndbox><text>men</text></object><object><name>Word</name><bndbox><xmin>384</xmin><xmax>403</xmax><ymin>426</ymin><ymax>439</ymax></bndbox><text>A</text></object><object><name>Word</name><bndbox><xmin>401</xmin><xmax>405</xmax><ymin>413</ymin><ymax>416</ymax></bndbox><text>.</text></object><object><name>Word</name><bndbox><xmin>386</xmin><xmax>406</xmax><ymin>460</ymin><ymax>538</ymax></bndbox><text>strong</text></object><bndbox><xmin>378</xmin><xmax>408</xmax><ymin>67</ymin><ymax>538</ymax></bndbox><text>to winning young men A . strong</text></object><object><name>TextLine</name><object><name>Word</name><bndbox><xmin>416</xmin><xmax>443</xmax><ymin>55</ymin><ymax>199</ymax></bndbox><text>temperance</text></object><object><name>Word</name><bndbox><xmin>424</xmin><xmax>438</xmax><ymin>243</ymin><ymax>356</ymax></bndbox><text>advocate</text></object><object><name>Word</name><bndbox><xmin>435</xmin><xmax>439</xmax><ymin>368</ymin><ymax>370</ymax></bndbox><text>,</text></object><object><name>Word</name><bndbox><xmin>421</xmin><xmax>446</xmax><ymin>390</ymin><ymax>510</ymax></bndbox><text>through</text></object><object><name>Word</name><bndbox><xmin>421</xmin><xmax>438</xmax><ymin>533</ymin><ymax>584</ymax></bndbox><text>the</text></object><bndbox><xmin>416</xmin><xmax>446</xmax><ymin>55</ymin><ymax>584</ymax></bndbox><text>temperance advocate , through the</text></object><object><name>TextLine</name><object><name>Word</name><bndbox><xmin>458</xmin><xmax>478</xmax><ymin>58</ymin><ymax>187</ymax></bndbox><text>influence</text></object><object><name>Word</name><bndbox><xmin>458</xmin><xmax>479</xmax><ymin>223</ymin><ymax>247</ymax></bndbox><text>of</text></object><object><name>Word</name><bndbox><xmin>467</xmin><xmax>480</xmax><ymin>288</ymin><ymax>302</ymax></bndbox><text>a</text></object><object><name>Word</name><object><name>Correction</name><bndbox><xmin>472</xmin><xmax>479</xmax><ymin>325</ymin><ymax>432</ymax></bndbox><text>canceling</text></object><bndbox><xmin>459</xmin><xmax>484</xmax><ymin>327</ymin><ymax>425</ymax></bndbox><text>canceling</text></object><object><name>Word</name><bndbox><xmin>457</xmin><xmax>480</xmax><ymin>444</ymin><ymax>563</ymax></bndbox><text>favorite</text></object><bndbox><xmin>457</xmin><xmax>484</xmax><ymin>58</ymin><ymax>563</ymax></bndbox><text>influence of a canceling favorite</text></object><object><name>TextLine</name><object><name>Word</name><bndbox><xmin>493</xmin><xmax>515</xmax><ymin>54</ymin><ymax>155</ymax></bndbox><text>teacher</text></object><object><name>Word</name><bndbox><xmin>510</xmin><xmax>516</xmax><ymin>170</ymin><ymax>171</ymax></bndbox><text>,</text></object><object><name>Word</name><bndbox><xmin>498</xmin><xmax>518</xmax><ymin>193</ymin><ymax>302</ymax></bndbox><text>Charles</text></object><object><name>Word</name><bndbox><xmin>494</xmin><xmax>516</xmax><ymin>349</ymin><ymax>469</ymax></bndbox><text>Stewart</text></object><object><name>Word</name><bndbox><xmin>510</xmin><xmax>518</xmax><ymin>481</ymin><ymax>482</ymax></bndbox><text>,</text></object><object><name>Word</name><bndbox><xmin>497</xmin><xmax>518</xmax><ymin>499</ymin><ymax>610</ymax></bndbox><text>another</text></object><bndbox><xmin>493</xmin><xmax>518</xmax><ymin>54</ymin><ymax>610</ymax></bndbox><text>teacher , Charles Stewart , another</text></object><object><name>TextLine</name><object><name>Word</name><bndbox><xmin>537</xmin><xmax>572</xmax><ymin>45</ymin><ymax>129</ymax></bndbox><text>Finney</text></object><object><name>Word</name><bndbox><xmin>540</xmin><xmax>559</xmax><ymin>161</ymin><ymax>257</ymax></bndbox><text>convert</text></object><object><name>Word</name><bndbox><xmin>552</xmin><xmax>552</xmax><ymin>270</ymin><ymax>270</ymax></bndbox><text>,</text></object><object><name>Word</name><bndbox><xmin>530</xmin><xmax>551</xmax><ymin>298</ymin><ymax>324</ymax></bndbox><text>he</text></object><object><name>Word</name><bndbox><xmin>536</xmin><xmax>557</xmax><ymin>354</ymin><ymax>459</ymax></bndbox><text>devoted</text></object><object><name>Word</name><bndbox><xmin>533</xmin><xmax>564</xmax><ymin>487</ymin><ymax>602</ymax></bndbox><text>himself</text></object><bndbox><xmin>530</xmin><xmax>572</xmax><ymin>45</ymin><ymax>602</ymax></bndbox><text>Finney convert , he devoted himself</text></object><object><name>TextLine</name><object><name>Word</name><bndbox><xmin>578</xmin><xmax>601</xmax><ymin>53</ymin><ymax>82</ymax></bndbox><text>to</text></object><object><name>Word</name><bndbox><xmin>582</xmin><xmax>600</xmax><ymin>97</ymin><ymax>146</ymax></bndbox><text>the</text></object><object><name>Word</name><bndbox><xmin>574</xmin><xmax>604</xmax><ymin>191</ymin><ymax>424</ymax></bndbox><text>anti-slavery</text></object><object><name>Word</name><bndbox><xmin>588</xmin><xmax>602</xmax><ymin>443</ymin><ymax>526</ymax></bndbox><text>cause</text></object><object><name>Word</name><bndbox><xmin>601</xmin><xmax>603</xmax><ymin>546</ymin><ymax>548</ymax></bndbox><text>.</text></object><bndbox><xmin>574</xmin><xmax>604</xmax><ymin>53</ymin><ymax>548</ymax></bndbox><text>to the anti-slavery cause .</text></object><bndbox><xmin>227</xmin><xmax>604</xmax><ymin>12</ymin><ymax>643</ymax></bndbox></object></annotation>