<annotation><filename>709.png</filename><folder>texts</folder><size><height>768</height><width>1024</width></size><object><name>TextBlock</name><object><name>TextLine</name><object><name>Word</name><bndbox><xmin>46</xmin><xmax>89</xmax><ymin>48</ymin><ymax>65</ymax></bndbox><text>Even</text></object><object><name>Word</name><bndbox><xmin>112</xmin><xmax>147</xmax><ymin>41</ymin><ymax>57</ymax></bndbox><text>the</text></object><object><name>Word</name><bndbox><xmin>167</xmin><xmax>295</xmax><ymin>35</ymin><ymax>56</ymax></bndbox><text>non-church</text></object><object><name>Word</name><bndbox><xmin>318</xmin><xmax>411</xmax><ymin>39</ymin><ymax>53</ymax></bndbox><text>mebers</text></object><object><name>Word</name><bndbox><xmin>438</xmin><xmax>446</xmax><ymin>45</ymin><ymax>48</ymax></bndbox><text>=</text></object><object><name>Word</name><bndbox><xmin>463</xmin><xmax>488</xmax><ymin>37</ymin><ymax>51</ymax></bndbox><text>the</text></object><object><name>Word</name><bndbox><xmin>518</xmin><xmax>626</xmax><ymin>34</ymin><ymax>60</ymax></bndbox><text>freewheelers</text></object><object><name>Word</name><bndbox><xmin>638</xmin><xmax>639</xmax><ymin>44</ymin><ymax>50</ymax></bndbox><text>,</text></object><bndbox><xmin>46</xmin><xmax>639</xmax><ymin>34</ymin><ymax>65</ymax></bndbox><text>Even the non-church mebers = the freewheelers ,</text></object><bndbox><xmin>46</xmin><xmax>639</xmax><ymin>34</ymin><ymax>65</ymax></bndbox></object><object><name>TextBlock</name><object><name>TextLine</name><object><name>Word</name><bndbox><xmin>373</xmin><xmax>460</xmax><ymin>400</ymin><ymax>429</ymax></bndbox><text>marginal</text></object><object><name>Word</name><bndbox><xmin>482</xmin><xmax>587</xmax><ymin>387</ymin><ymax>423</ymax></bndbox><text>religionists</text></object><object><name>Word</name><bndbox><xmin>603</xmin><xmax>641</xmax><ymin>387</ymin><ymax>402</ymax></bndbox><text>and</text></object><object><name>Word</name><bndbox><xmin>657</xmin><xmax>675</xmax><ymin>391</ymin><ymax>401</ymax></bndbox><text>to</text></object><object><name>Word</name><bndbox><xmin>682</xmin><xmax>698</xmax><ymin>395</ymin><ymax>402</ymax></bndbox><text>on</text></object><bndbox><xmin>373</xmin><xmax>698</xmax><ymin>387</ymin><ymax>429</ymax></bndbox><text>marginal religionists and to on</text></object><object><name>TextLine</name><object><name>Word</name><bndbox><xmin>375</xmin><xmax>376</xmax><ymin>443</ymin><ymax>443</ymax></bndbox><text>-</text></object><object><name>Word</name><bndbox><xmin>387</xmin><xmax>387</xmax><ymin>442</ymin><ymax>443</ymax></bndbox><text>-</text></object><object><name>Word</name><bndbox><xmin>412</xmin><xmax>461</xmax><ymin>428</ymin><ymax>446</ymax></bndbox><text>have</text></object><object><name>Word</name><bndbox><xmin>470</xmin><xmax>497</xmax><ymin>426</ymin><ymax>442</ymax></bndbox><text>the</text></object><object><name>Word</name><bndbox><xmin>517</xmin><xmax>565</xmax><ymin>421</ymin><ymax>437</ymax></bndbox><text>values</text></object><object><name>Word</name><bndbox><xmin>574</xmin><xmax>595</xmax><ymin>418</ymin><ymax>443</ymax></bndbox><text>of</text></object><object><name>Word</name><bndbox><xmin>604</xmin><xmax>675</xmax><ymin>417</ymin><ymax>433</ymax></bndbox><text>christian</text></object><bndbox><xmin>375</xmin><xmax>675</xmax><ymin>417</ymin><ymax>446</ymax></bndbox><text>- - have the values of christian</text></object><object><name>TextLine</name><object><name>Word</name><bndbox><xmin>379</xmin><xmax>477</xmax><ymin>453</ymin><ymax>476</ymax></bndbox><text>civilization</text></object><object><name>Word</name><bndbox><xmin>496</xmin><xmax>599</xmax><ymin>449</ymin><ymax>468</ymax></bndbox><text>internalized</text></object><object><name>Word</name><bndbox><xmin>614</xmin><xmax>631</xmax><ymin>448</ymin><ymax>462</ymax></bndbox><text>in</text></object><object><name>Word</name><bndbox><xmin>640</xmin><xmax>680</xmax><ymin>445</ymin><ymax>457</ymax></bndbox><text>them</text></object><object><name>Word</name><bndbox><xmin>696</xmin><xmax>696</xmax><ymin>457</ymin><ymax>457</ymax></bndbox><text>.</text></object><bndbox><xmin>379</xmin><xmax>696</xmax><ymin>445</ymin><ymax>476</ymax></bndbox><text>civilization internalized in them .</text></object><object><name>TextLine</name><object><name>Word</name><bndbox><xmin>379</xmin><xmax>408</xmax><ymin>491</ymin><ymax>507</ymax></bndbox><text>For</text></object><object><name>Word</name><bndbox><xmin>424</xmin><xmax>489</xmax><ymin>484</ymin><ymax>514</ymax></bndbox><text>example</text></object><object><name>Word</name><bndbox><xmin>495</xmin><xmax>497</xmax><ymin>496</ymin><ymax>502</ymax></bndbox><text>,</text></object><object><name>Word</name><bndbox><xmin>509</xmin><xmax>554</xmax><ymin>483</ymin><ymax>498</ymax></bndbox><text>those</text></object><object><name>Word</name><bndbox><xmin>574</xmin><xmax>656</xmax><ymin>475</ymin><ymax>506</ymax></bndbox><text>regarding</text></object><object><name>Word</name><bndbox><xmin>664</xmin><xmax>690</xmax><ymin>474</ymin><ymax>489</ymax></bndbox><text>not</text></object><object><name>Word</name><bndbox><xmin>694</xmin><xmax>695</xmax><ymin>485</ymin><ymax>486</ymax></bndbox><text>.</text></object><bndbox><xmin>379</xmin><xmax>695</xmax><ymin>474</ymin><ymax>514</ymax></bndbox><text>For example , those regarding not .</text></object><object><name>TextLine</name><object><name>Word</name><bndbox><xmin>385</xmin><xmax>422</xmax><ymin>517</ymin><ymax>538</ymax></bndbox><text>erial</text></object><object><name>Word</name><bndbox><xmin>439</xmin><xmax>504</xmax><ymin>513</ymin><ymax>529</ymax></bndbox><text>objects</text></object><object><name>Word</name><bndbox><xmin>522</xmin><xmax>559</xmax><ymin>506</ymin><ymax>526</ymax></bndbox><text>and</text></object><object><name>Word</name><bndbox><xmin>573</xmin><xmax>667</xmax><ymin>508</ymin><ymax>536</ymax></bndbox><text>pragmatic</text></object><bndbox><xmin>385</xmin><xmax>667</xmax><ymin>506</ymin><ymax>538</ymax></bndbox><text>erial objects and pragmatic</text></object><object><name>TextLine</name><object><name>Word</name><bndbox><xmin>387</xmin><xmax>439</xmax><ymin>545</ymin><ymax>568</ymax></bndbox><text>ends</text></object><object><name>Word</name><bndbox><xmin>455</xmin><xmax>456</xmax><ymin>558</ymin><ymax>560</ymax></bndbox><text>.</text></object><bndbox><xmin>387</xmin><xmax>456</xmax><ymin>545</ymin><ymax>568</ymax></bndbox><text>ends .</text></object><bndbox><xmin>373</xmin><xmax>698</xmax><ymin>387</ymin><ymax>568</ymax></bndbox></object><object><name>Diagram</name><object><name>Drawing</name><bndbox><xmin>114</xmin><xmax>561</xmax><ymin>128</ymin><ymax>357</ymax></bndbox></object><object><name>TextLine</name><object><name>Word</name><bndbox><xmin>357</xmin><xmax>393</xmax><ymin>279</ymin><ymax>293</ymax></bndbox><text>T.E.6</text></object><bndbox><xmin>357</xmin><xmax>393</xmax><ymin>279</ymin><ymax>293</ymax></bndbox><text>T.E.6</text></object><object><name>TextLine</name><object><name>Word</name><bndbox><xmin>129</xmin><xmax>163</xmax><ymin>301</ymin><ymax>310</ymax></bndbox><text>T.E.5</text></object><bndbox><xmin>129</xmin><xmax>163</xmax><ymin>301</ymin><ymax>310</ymax></bndbox><text>T.E.5</text></object><object><name>TextLine</name><object><name>Word</name><bndbox><xmin>125</xmin><xmax>180</xmax><ymin>144</ymin><ymax>157</ymax></bndbox><text>Terminal</text></object><object><name>Word</name><bndbox><xmin>203</xmin><xmax>265</xmax><ymin>135</ymin><ymax>153</ymax></bndbox><text>Element</text></object><object><name>Word</name><bndbox><xmin>281</xmin><xmax>282</xmax><ymin>132</ymin><ymax>135</ymax></bndbox><text>1</text></object><bndbox><xmin>125</xmin><xmax>282</xmax><ymin>132</ymin><ymax>157</ymax></bndbox><text>Terminal Element 1</text></object><object><name>TextLine</name><object><name>Word</name><bndbox><xmin>302</xmin><xmax>373</xmax><ymin>181</ymin><ymax>197</ymax></bndbox><text>Terminal</text></object><object><name>Word</name><bndbox><xmin>386</xmin><xmax>427</xmax><ymin>173</ymin><ymax>190</ymax></bndbox><text>Element</text></object><object><name>Word</name><bndbox><xmin>431</xmin><xmax>433</xmax><ymin>174</ymin><ymax>183</ymax></bndbox><text>2</text></object><bndbox><xmin>302</xmin><xmax>433</xmax><ymin>173</ymin><ymax>197</ymax></bndbox><text>Terminal Element 2</text></object><bndbox><xmin>114</xmin><xmax>561</xmax><ymin>128</ymin><ymax>357</ymax></bndbox></object><object><name>Drawing</name><bndbox><xmin>112</xmin><xmax>357</xmax><ymin>567</ymin><ymax>818</ymax></bndbox></object><object><name>List</name><object><name>TextLine</name><object><name>Symbol</name><bndbox><xmin>407</xmin><xmax>413</xmax><ymin>656</ymin><ymax>661</ymax></bndbox></object><object><name>Word</name><bndbox><xmin>427</xmin><xmax>488</xmax><ymin>643</ymin><ymax>661</ymax></bndbox><text>rustler</text></object><bndbox><xmin>407</xmin><xmax>488</xmax><ymin>643</ymin><ymax>661</ymax></bndbox><text>rustler</text></object><object><name>TextLine</name><object><name>Symbol</name><bndbox><xmin>414</xmin><xmax>416</xmax><ymin>682</ymin><ymax>685</ymax></bndbox></object><object><name>Word</name><bndbox><xmin>426</xmin><xmax>505</xmax><ymin>665</ymin><ymax>688</ymax></bndbox><text>transition</text></object><bndbox><xmin>414</xmin><xmax>505</xmax><ymin>665</ymin><ymax>688</ymax></bndbox><text>transition</text></object><object><name>TextLine</name><object><name>Symbol</name><bndbox><xmin>414</xmin><xmax>417</xmax><ymin>709</ymin><ymax>712</ymax></bndbox></object><object><name>Word</name><bndbox><xmin>428</xmin><xmax>490</xmax><ymin>690</ymin><ymax>725</ymax></bndbox><text>regard</text></object><bndbox><xmin>414</xmin><xmax>490</xmax><ymin>690</ymin><ymax>725</ymax></bndbox><text>regard</text></object><object><name>TextLine</name><object><name>Symbol</name><bndbox><xmin>418</xmin><xmax>422</xmax><ymin>735</ymin><ymax>740</ymax></bndbox></object><object><name>Word</name><bndbox><xmin>432</xmin><xmax>518</xmax><ymin>722</ymin><ymax>740</ymax></bndbox><text>memories</text></object><bndbox><xmin>418</xmin><xmax>518</xmax><ymin>722</ymin><ymax>740</ymax></bndbox><text>memories</text></object><object><name>TextLine</name><object><name>Symbol</name><bndbox><xmin>418</xmin><xmax>421</xmax><ymin>766</ymin><ymax>770</ymax></bndbox></object><object><name>Word</name><bndbox><xmin>434</xmin><xmax>477</xmax><ymin>750</ymin><ymax>769</ymax></bndbox><text>need</text></object><bndbox><xmin>418</xmin><xmax>477</xmax><ymin>750</ymin><ymax>770</ymax></bndbox><text>need</text></object><bndbox><xmin>407</xmin><xmax>518</xmax><ymin>643</ymin><ymax>770</ymax></bndbox></object></annotation>